sam/ConfigEnvy.py
sam/__init__.py
sam/common.py
sam/constants.py
sam/default.cfg
sam/errors.py
sam/httpserver.py
sam/integrity.py
sam/launcher.py
sam/preprocess.py
sam/server_aggregator.py
sam/server_collector.py
sam/server_webserver.py
sam/update_portLUT.py
sam/importers/__init__.py
sam/importers/import_asasyslog.py
sam/importers/import_aws.py
sam/importers/import_base.py
sam/importers/import_netflow.py
sam/importers/import_paloalto.py
sam/importers/import_tcpdump.py
sam/importers/import_tshark.py
sam/importers/netflow_collector.py
sam/local/__init__.py
sam/local/en.py
sam/local/fr.py
sam/local/rv.py
sam/models/__init__.py
sam/models/base.py
sam/models/datasources.py
sam/models/details.py
sam/models/filters.py
sam/models/links.py
sam/models/livekeys.py
sam/models/nodes.py
sam/models/ports.py
sam/models/settings.py
sam/models/strings.py
sam/models/subscriptions.py
sam/models/tables.py
sam/models/upload.py
sam/models/user.py
sam/models/whois.py
sam/models/security/__init__.py
sam/models/security/alerts.py
sam/models/security/anomaly_plugin.py
sam/models/security/rule.py
sam/models/security/rule_parser.py
sam/models/security/rule_template.py
sam/models/security/rules.py
sam/models/security/ruling_process.py
sam/models/security/warnings.py
sam/pages/__init__.py
sam/pages/alerts.py
sam/pages/anomaly_plugin.py
sam/pages/base.py
sam/pages/details.py
sam/pages/links.py
sam/pages/login.py
sam/pages/logout.py
sam/pages/map.py
sam/pages/metadata.py
sam/pages/nodes.py
sam/pages/portinfo.py
sam/pages/rules.py
sam/pages/sec_dashboard.py
sam/pages/settings.py
sam/pages/settings_page.py
sam/pages/stats.py
sam/pages/table.py
sam/rule_templates/compromised.yml
sam/rule_templates/compromised_hosts.txt
sam/rule_templates/dos.yml
sam/rule_templates/netscan.yml
sam/rule_templates/portscan.yml
sam/rule_templates/suspicious.yml
sam/sql/default_port_data.json
sam/sql/delete_staging_data.sql
samapper-0.3.2.dist-info/DESCRIPTION.rst
samapper-0.3.2.dist-info/METADATA
samapper-0.3.2.dist-info/RECORD
samapper-0.3.2.dist-info/WHEEL
samapper-0.3.2.dist-info/entry_points.txt
samapper-0.3.2.dist-info/metadata.json
samapper-0.3.2.dist-info/top_level.txt
