Metadata-Version: 2.0
Name: samapper
Version: 0.3.2
Summary: System Architecture Mapping tool
Home-page: https://github.com/riolet/sam
Author: Riolet
Author-email: joe.pelz@gmail.com
License: GPLv3
Platform: UNKNOWN
Classifier: Development Status :: 3 - Alpha
Classifier: License :: OSI Approved :: GNU General Public License v3 (GPLv3)
Classifier: Programming Language :: Python :: 2
Classifier: Programming Language :: Python :: 2.7
Requires-Dist: MySQL-python (>=1.2.5)
Requires-Dist: PyYAML (>=3.10)
Requires-Dist: requests (>=2.18)
Requires-Dist: web.py (>=0.38)
Provides-Extra: dev
Requires-Dist: jasmine (>=2.8); extra == 'dev'
Requires-Dist: pytest (>=3.2); extra == 'dev'
